gt_telem/__init__.py
gt_telem/turismo_client.py
gt_telem/errors/__init__.py
gt_telem/errors/playstation_errors.py
gt_telem/events/__init__.py
gt_telem/events/driver_events.py
gt_telem/events/game_events.py
gt_telem/events/race_events.py
gt_telem/models/__init__.py
gt_telem/models/helpers.py
gt_telem/models/models.py
gt_telem/models/telemetry.py
gt_telem/models/telemetry_packet.py
gt_telem/net/__init__.py
gt_telem/net/crypto.py
gt_telem/net/device_discover.py
gt_telem-0.2.9.dist-info/LICENSE
gt_telem-0.2.9.dist-info/METADATA
gt_telem-0.2.9.dist-info/WHEEL
gt_telem-0.2.9.dist-info/top_level.txt
gt_telem-0.2.9.dist-info/RECORD
