Metadata-Version: 2.1
Name: gt-telem
Version: 0.2.9
Summary: Library to interface with Gran Turismo's motion rig telemetry service.
Author-email: Jonpro03 <jonpro03@gmail.com>
License: GNU GENERAL PUBLIC LICENSE
Project-URL: Homepage, https://github.com/RaceCrewAI
Keywords: gran,turismo
Classifier: License :: OSI Approved :: GNU Lesser General Public License v3 (LGPLv3)
Classifier: Programming Language :: Python :: 3
Requires-Python: >=3.10
License-File: LICENSE
Requires-Dist: salsa20 >=0.3.0
Provides-Extra: dev
Requires-Dist: black ; extra == 'dev'
Requires-Dist: bumpver ; extra == 'dev'
Requires-Dist: isort ; extra == 'dev'
Requires-Dist: pandas ; extra == 'dev'
Requires-Dist: pre-commit ; extra == 'dev'
